pkgbuild_language_server/__init__.py
pkgbuild_language_server-0.0.7.dist-info/LICENSE
pkgbuild_language_server-0.0.7.dist-info/METADATA
pkgbuild_language_server-0.0.7.dist-info/WHEEL
pkgbuild_language_server-0.0.7.dist-info/top_level.txt
pkgbuild_language_server-0.0.7.dist-info/RECORD
